macrodemos/__init__.py
macrodemos/captura.py
macrodemos/common_components.py
macrodemos/constants.py
macrodemos/demo_ARMA.py
macrodemos/demo_BoxJenkins.py
macrodemos/demo_Markov.py
macrodemos/demo_Solow.py
macrodemos/demo_filters.py
macrodemos/data/CRI-initial-data.csv
macrodemos/data/IFS_GDP.xlsx
macrodemos/data/national_accounts.xlsx
macrodemos-2025.4.10.dist-info/METADATA
macrodemos-2025.4.10.dist-info/WHEEL
macrodemos-2025.4.10.dist-info/top_level.txt
macrodemos-2025.4.10.dist-info/RECORD
