Metadata-Version: 2.4
Name: macrodemos
Version: 2025.4.10
Summary: Demo programs to learn macroeconomics and macro-econometrics concepts
Home-page: http://randall-romero.com/code/macrodemos
Author: Randall Romero-Aguilar
Author-email: randall.romero@outlook.com
License: MIT
Keywords: time series,ARMA,filters,Markov chain,Solow-Swan,Hodrick-Prescott,Baxter-King
Requires-Python: >=3.7
Requires-Dist: beautifulsoup4>=4.12
Requires-Dist: pandas>=2.2
Requires-Dist: numpy>=2.0
Requires-Dist: plotly>=6.0.0
Requires-Dist: dash>=3.0.0
Requires-Dist: statsmodels>=0.14
Requires-Dist: jupyter-dash>=0.4.0
Requires-Dist: lxml>=5.2
Requires-Dist: openpyxl>=3.0.0
Requires-Dist: requests>=2.30
Requires-Dist: scipy>=1.15
Dynamic: author
Dynamic: author-email
Dynamic: description
Dynamic: description-content-type
Dynamic: home-page
Dynamic: keywords
Dynamic: license
Dynamic: requires-dist
Dynamic: requires-python
Dynamic: summary
